AUTHORS
LICENSE
MANIFEST.in
README.rst
setup.cfg
setup.py
docs/Makefile
docs/conf.py
docs/index.rst
docs/installation.rst
docs/make.bat
docs/usage.rst
docs/api/exceptions.rst
docs/api/index.rst
docs/api/manager.rst
docs/api/sockets.rst
pyhs/__init__.py
pyhs/exceptions.py
pyhs/manager.py
pyhs/sockets.py
pyhs/utils.py
python_handler_socket.egg-info/PKG-INFO
python_handler_socket.egg-info/SOURCES.txt
python_handler_socket.egg-info/dependency_links.txt
python_handler_socket.egg-info/top_level.txt