Metadata-Version: 1.0
Name: python-handler-socket
Version: 0.2.0
Summary: ====
